mimo_keras/__init__.py
mimo_keras/preprocessing.py
mimo_keras/utils.py
mimo_keras-0.1.17.dist-info/LICENSE
mimo_keras-0.1.17.dist-info/METADATA
mimo_keras-0.1.17.dist-info/WHEEL
mimo_keras-0.1.17.dist-info/top_level.txt
mimo_keras-0.1.17.dist-info/RECORD
