Metadata-Version: 2.1
Name: mimo-keras
Version: 0.1.17
Summary: A DataGenerator for Keras multiple-input multiple-output models and massive datasets with any type of data
Home-page: https://github.com/simkarwin/mimo_keras
Download-URL: https://github.com/simkarwin/mimo_keras/archive/V0.1.17.tar.gz
Author: Simkarwin
Author-email: simkarwin@gmail.com
License: MIT
Keywords: keras data generator,data generator,multi-input multi-output model,medical image processing
License-File: LICENSE
Requires-Dist: numpy (>=1.0.0)
Requires-Dist: pandas (>=1.0.0)
Requires-Dist: keras (>=2.0.0)
